faker_ru_pii/__init__.py
faker_ru_pii/ru_birth_certificate_provider.py
faker_ru_pii/ru_driver_license.py
faker_ru_pii/ru_education_provider.py
faker_ru_pii/ru_foreign_passport_provider.py
faker_ru_pii/ru_migration_card_provider.py
faker_ru_pii/ru_military_id_provider.py
faker_ru_pii/ru_passport_provider.py
faker_ru_pii/ru_residence_permit_provider.py
faker_ru_pii-0.1.0.dist-info/licenses/LICENSE
tests/__init__.py
tests/conftest.py
tests/test_birth_certificate_provider.py
tests/test_driver_license.py
tests/test_education_provider.py
tests/test_foreign_passport_provider.py
tests/test_migration_card_provider.py
tests/test_military_id_provider.py
tests/test_passport_provider.py
tests/test_residence_permit_provider.py
faker_ru_pii-0.1.0.dist-info/METADATA
faker_ru_pii-0.1.0.dist-info/WHEEL
faker_ru_pii-0.1.0.dist-info/top_level.txt
faker_ru_pii-0.1.0.dist-info/RECORD
