Metadata-Version: 2.4
Name: faker-ru-pii
Version: 0.1.0
Summary: Faker provider for Russian PII data generation
Home-page: https://github.com/ivanboldyrevv/faker-ru-pii
Author: Ivan Boldyrev
Author-email: Ivan Boldyrev <iaboldyrev032@gmail.com>
License: MIT
Project-URL: Homepage, https://github.com/ivanboldyrevv/faker_ru_pii
Project-URL: Repository, https://github.com/ivanboldyrevv/faker-ru-pii
Project-URL: Bug Tracker, https://github.com/ivanboldyrevv/faker-ru-pii/issues
Classifier: Intended Audience :: Developers
Classifier: License :: OSI Approved :: MIT License
Classifier: Programming Language :: Python :: 3.10
Classifier: Programming Language :: Python :: 3.11
Classifier: Programming Language :: Python :: 3.12
Classifier: Topic :: Software Development :: Testing
Classifier: Topic :: Software Development :: Libraries :: Python Modules
Requires-Python: >=3.10
License-File: LICENSE
Requires-Dist: Faker>=39.0.0
Provides-Extra: dev
Requires-Dist: pytest>=9.0.2; extra == "dev"
Dynamic: author
Dynamic: home-page
Dynamic: license-file
Dynamic: requires-python
